LICENSE
README.md
pyproject.toml
setup.py
deps/requirements.in
src/slack_helpers/__init__.py
src/slack_helpers/_version.py
src/slack_helpers/interactive.py
src/slack_helpers/send_only.py
src/slack_helpers.egg-info/PKG-INFO
src/slack_helpers.egg-info/SOURCES.txt
src/slack_helpers.egg-info/dependency_links.txt
src/slack_helpers.egg-info/entry_points.txt
src/slack_helpers.egg-info/requires.txt
src/slack_helpers.egg-info/top_level.txt
src/slack_helpers/cli/__init__.py
src/slack_helpers/cli/main.py
src/slack_helpers/health/__init__.py
src/slack_helpers/health/font.py
src/slack_helpers/health/slack.py
src/slack_helpers/utils/__init__.py
src/slack_helpers/utils/log.py
src/slack_helpers/utils/rich.py