Metadata-Version: 2.1
Name: slack-helpers
Version: 0.0.0
Summary: Send traceback, matplotlib, pillow, PDB etc. on Slack and preview them with ease.
Author: Kiyoon Kim
License:                                  Apache License
Project-URL: Homepage, https://github.com/deargen/slack-helpers
Keywords: slack,wrapper,helper,viewer
Classifier: Programming Language :: Python
Classifier: Programming Language :: Python :: 3
Classifier: Programming Language :: Python :: 3.10
Classifier: Programming Language :: Python :: 3.11
Classifier: Programming Language :: Python :: 3.12
Requires-Python: <4,>=3.10
License-File: LICENSE
Requires-Dist: rich>=13.0.0
Requires-Dist: tqdm>=4.0.0
Requires-Dist: pillow
Requires-Dist: matplotlib
Requires-Dist: slack-bolt
Requires-Dist: clearml
Requires-Dist: ansi2html
Requires-Dist: cairosvg
Requires-Dist: typer>=0.12.4
